glennopt/.gitignore
glennopt/DOE/Experiment.py
glennopt/DOE/__init__.py
glennopt/__init__.py
glennopt/base/__init__.py
glennopt/base/individual.py
glennopt/base/optimizer.py
glennopt/base/parameter.py
glennopt/helpers/MultiLayerLinear.py
glennopt/helpers/__init__.py
glennopt/helpers/convert_to_ndarray.py
glennopt/helpers/copy_helper.py
glennopt/helpers/jacobian.py
glennopt/helpers/list_functions.py
glennopt/helpers/mutate.py
glennopt/helpers/nn_helpers.py
glennopt/helpers/nsga_functions.py
glennopt/helpers/parallel_settings.py
glennopt/helpers/population_distance.py
glennopt/helpers/post_processing.py
glennopt/helpers/read_input_file.py
glennopt/io/read_json.py
glennopt/io/write_json.py
glennopt/optimizers/__init__.py
glennopt/optimizers/nsga3.py
glennopt/optimizers/nsga3_ml.py
glennopt/optimizers/nsopt.py
glennopt/optimizers/sode.py
glennopt-1.5.2.dist-info/METADATA
glennopt-1.5.2.dist-info/WHEEL
glennopt-1.5.2.dist-info/RECORD
